boto_s3_router/__init__.py
boto_s3_router/botos3router.py
tests/__init__.py
tests/test_client.py
boto_s3_router-0.0.3.dist-info/LICENSE
boto_s3_router-0.0.3.dist-info/METADATA
boto_s3_router-0.0.3.dist-info/WHEEL
boto_s3_router-0.0.3.dist-info/top_level.txt
boto_s3_router-0.0.3.dist-info/RECORD
