Metadata-Version: 2.1
Name: boto-s3-router
Version: 0.0.3
Summary: Provides a Boto3-like client routing requests to multiple S3 clients
Home-page: https://github.com/treeverse/boto-s3-router
Author: Treeverse
Author-email: services@treeverse.io
License: UNKNOWN
Keywords: boto,boto3,lakeFS,minio,AWS,s3,router
Platform: UNKNOWN
Requires-Python: >=3.6
License-File: LICENSE
Requires-Dist: boto3
Requires-Dist: fnmatch2
